lazy_ops/__init__.py
lazy_ops/lazy_loading.py
lazy_ops-0.2.0.dist-info/LICENSE
lazy_ops-0.2.0.dist-info/METADATA
lazy_ops-0.2.0.dist-info/WHEEL
lazy_ops-0.2.0.dist-info/top_level.txt
lazy_ops-0.2.0.dist-info/RECORD
