Metadata-Version: 2.1
Name: lazy_ops
Version: 0.2.0
Summary: Lazy slicing and transpose operations for h5py and zarr
Home-page: https://github.com/ben-dichter-consulting/lazy_ops
Author: Daniel Sotoude, Ben Dichter
Author-email: dsot@protonmail.com, ben.dichter@gmail.com
License: UNKNOWN
Platform: UNKNOWN
Classifier: Operating System :: OS Independent
Classifier: Development Status :: 3 - Alpha
Classifier: License :: OSI Approved :: BSD License
Classifier: Programming Language :: Python :: 3.6
Classifier: Programming Language :: Python :: 3.7
